bratly/__init__.py
bratly/annotation_types.py
bratly/collection_types.py
bratly/exceptions.py
bratly/py.typed
bratly-0.1.4.dist-info/WHEEL
bratly-0.1.4.dist-info/METADATA
bratly-0.1.4.dist-info/RECORD
